visor/__init__.py
visor/visor.py
visor-0.1.2.dist-info/WHEEL
visor-0.1.2.dist-info/METADATA
visor-0.1.2.dist-info/RECORD
