Metadata-Version: 2.1
Name: visor
Version: 0.1.2
Summary: Makes background process management easy
License: MIT
Author-email: Ankit Saini <visorme@nkit.dev>
Requires-Python: >=3.7
Project-URL: Homepage, https://github.com/nkitsaini/visor
Project-URL: Repository, https://github.com/nkitsaini/visor
